handlebar_core/__init__.py
handlebar_core/api/manager.py
handlebar_core/api/types.py
handlebar_core/engine.py
handlebar_core/index.py
handlebar_core/rules.py
handlebar_core/telemetry/__init__.py
handlebar_core/telemetry/types.py
handlebar_core/types.py
handlebar_core/utils.py
handlebar_core-0.1.0.dist-info/WHEEL
handlebar_core-0.1.0.dist-info/METADATA
handlebar_core-0.1.0.dist-info/RECORD
