Metadata-Version: 2.4
Name: handlebar-core
Version: 0.1.0
Summary: Core primitives for Handlebar agentic AI governance
Keywords: governance,ai,agent,llm,guardrails,handlebar,safety
Author: Handlebar Team
Author-email: Handlebar Team <contact@gethandlebar.com>
License-Expression: Apache-2.0
Requires-Python: >=3.13
Project-URL: Homepage, https://gethandlebar.com
Project-URL: Issues, https://github.com/gethandlebar/handlebar-python/issues
Project-URL: Repository, https://github.com/gethandlebar/handlebar-python
